whatsappas/__init__.py
whatsappas-2.0.0.dist-info/LICENSE.txt
whatsappas-2.0.0.dist-info/METADATA
whatsappas-2.0.0.dist-info/WHEEL
whatsappas-2.0.0.dist-info/top_level.txt
whatsappas-2.0.0.dist-info/RECORD
