Metadata-Version: 2.1
Name: whatsappas
Version: 2.0.0
Summary: Whatsapp automatic sender of messages/photos
Home-page: https://github.com/guilhermehuther/whatsapp_automatic_sender
Author: Guilherme Huther Baldo
Author-email: guilhermehuther@gmail.com
Classifier: Programming Language :: Python :: 3
Classifier: License :: OSI Approved :: MIT License
Classifier: Operating System :: OS Independent
Requires-Python: >=3.7
License-File: LICENSE.txt
